{
  "success": true,
  "results": [
    {
      "title": "Iran Radio Stations: Persian Radio",
      "appId": "com.asemob.radioapp.Iran",
      "url": "https://play.google.com/store/apps/details?id=com.asemob.radioapp.Iran",
      "icon": "https://play-lh.googleusercontent.com/1QGIurh8b_iEn1sCdNkhcePyAeDDiZmJYqnR3WIZAS8AjCTSOSp-ToDl12-od3sqrw",
      "developer": "Ase.Mob",
      "developerId": "8797606602150852799",
      "priceText": "FREE",
      "price": 0,
      "free": true,
      "summary": "Choose your favorite radio station from the IRAN and listen live 📻 .",
      "scoreText": "4.7",
      "score": 4.6930695
    },
    {
      "title": "Hausa Radio Stations: Radio Hausa",
      "appId": "com.asemob.radioapp.Hausa",
      "url": "https://play.google.com/store/apps/details?id=com.asemob.radioapp.Hausa",
      "icon": "https://play-lh.googleusercontent.com/XC0Cnr5Uh0HnsLam4ItvHWKDoPq4qAg7f1p9fIhyonwwDO2F4mkYSLcvDYqY78CfBbw",
      "developer": "Ase.Mob",
      "developerId": "8797606602150852799",
      "priceText": "FREE",
      "price": 0,
      "free": true,
      "summary": "Choose your favorite radio station from the HAUSA and listen live 📻 .",
      "scoreText": "4.6",
      "score": 4.5531917
    },
    {
      "title": "Mali Radio Stations: Radio Mali",
      "appId": "com.asemob.radioapp.Mali",
      "url": "https://play.google.com/store/apps/details?id=com.asemob.radioapp.Mali",
      "icon": "https://play-lh.googleusercontent.com/EyrNor_3P5L5QIWuB8jWpf29yiFbWe2wiuYkIdKYcj28UFqON5UPGxB1GWw5jxmVMmU",
      "developer": "Ase.Mob",
      "developerId": "8797606602150852799",
      "priceText": "FREE",
      "price": 0,
      "free": true,
      "summary": "Choose your favorite radio station from the MALI and listen live 📻 .",
      "scoreText": "4.8",
      "score": 4.76
    },
    {
      "title": "Armenian Radio Stations: ArmRadio",
      "appId": "com.asemob.radioapp.Armenia",
      "url": "https://play.google.com/store/apps/details?id=com.asemob.radioapp.Armenia",
      "icon": "https://play-lh.googleusercontent.com/Kc3VL1V9cYuT8nZv9_RVlGfJ95HbAnO7Z007ZPSg0absaNAYPpijApfwhTr_on1OddI",
      "developer": "Ase.Mob",
      "developerId": "8797606602150852799",
      "priceText": "FREE",
      "price": 0,
      "free": true,
      "summary": "Choose your favorite radio station from the ARMENIA and listen live 📻 .",
      "scoreText": "4.7",
      "score": 4.6842103
    },
    {
      "title": "Afghan Radio Stations: Radio Afghanistan",
      "appId": "com.asemob.afradio",
      "url": "https://play.google.com/store/apps/details?id=com.asemob.afradio",
      "icon": "https://play-lh.googleusercontent.com/Ji1jOIiHYXSY-q80zX0sXTLb7YWvaJ5YPl9sgxyxvdYvoZaQiC1orGvKl-4ETLmnPA",
      "developer": "Ase.Mob",
      "developerId": "8797606602150852799",
      "priceText": "FREE",
      "price": 0,
      "free": true,
      "summary": "Choose your favorite radio station from the AFGHANISTAN and listen live 📻 .",
      "scoreText": "0.0",
      "score": 0
    },
    {
      "title": "Tanzania Radio Stations: Radio Tanzania",
      "appId": "com.asemob.radioapp.Tanzania",
      "url": "https://play.google.com/store/apps/details?id=com.asemob.radioapp.Tanzania",
      "icon": "https://play-lh.googleusercontent.com/SuH2IzBA3UbUXSHfx_4F6-IfdwbXAC6hGEO9N1JN3gR3cZL1GIkuqEnaugY4o_6Idw",
      "developer": "Ase.Mob",
      "developerId": "8797606602150852799",
      "priceText": "FREE",
      "price": 0,
      "free": true,
      "summary": "Choose your favorite radio station from the TANZANIA and listen live 📻 .",
      "scoreText": "0.0",
      "score": 0
    },
    {
      "title": "Uganda Radio Stations: Radio Uganda",
      "appId": "com.asemob.radioapp.Uganda",
      "url": "https://play.google.com/store/apps/details?id=com.asemob.radioapp.Uganda",
      "icon": "https://play-lh.googleusercontent.com/iDqHfeeLOmiTCOC9KFMGyuUl_f7EQsGL-5DkztrnNN6j6t271t37uVyvVk4ICBaCnw",
      "developer": "Ase.Mob",
      "developerId": "8797606602150852799",
      "priceText": "FREE",
      "price": 0,
      "free": true,
      "summary": "Choose your favorite radio station from the UGANDA and listen live 📻 .",
      "scoreText": "0.0",
      "score": 0
    },
    {
      "title": "Jamaica Radio Stations: Radio Jamaica",
      "appId": "com.asemob.radioapp.Jamaican",
      "url": "https://play.google.com/store/apps/details?id=com.asemob.radioapp.Jamaican",
      "icon": "https://play-lh.googleusercontent.com/b6BhQ6xMy4yIOzUtrndswOdEExcYoGoyBHy75oOPiO1GYebitMZ9XWAPLlbbo04CD2I",
      "developer": "Ase.Mob",
      "developerId": "8797606602150852799",
      "priceText": "FREE",
      "price": 0,
      "free": true,
      "summary": "Choose your favorite radio station from the JAMAICA and listen live 📻 .",
      "scoreText": "0.0",
      "score": 0
    },
    {
      "title": "Pakistani Radio Stations: Radio Pakistan",
      "appId": "com.asemob.radioapp.Pakistan",
      "url": "https://play.google.com/store/apps/details?id=com.asemob.radioapp.Pakistan",
      "icon": "https://play-lh.googleusercontent.com/lPbcuBK4aGg54-DpUFMdtw4oWL4H4yimKZXuDWMQH-R2pi2g7TvuFm-Q0-RCdPjKg04",
      "developer": "Ase.Mob",
      "developerId": "8797606602150852799",
      "priceText": "FREE",
      "price": 0,
      "free": true,
      "summary": "Choose your favorite radio station from the PAKISTAN and listen live 📻 .",
      "scoreText": "4.6",
      "score": 4.631579
    },
    {
      "title": "Curaçao Radio Stations: Radio Curaçao",
      "appId": "com.asemob.radioapp.Curacao",
      "url": "https://play.google.com/store/apps/details?id=com.asemob.radioapp.Curacao",
      "icon": "https://play-lh.googleusercontent.com/3JuEQ4GLobofnBFCxR6dtu5JsPZVdIC5jPSWGX7CFTYdHc3RTAMgd1Ht06IZS8AoVEzR",
      "developer": "Ase.Mob",
      "developerId": "8797606602150852799",
      "priceText": "FREE",
      "price": 0,
      "free": true,
      "summary": "Choose your favorite radio station from the CURAÇAO and listen live 📻 .",
      "scoreText": "0.0",
      "score": 0
    },
    {
      "title": "Ghana Radio Stations: Radio Ghana",
      "appId": "com.asemob.radioapp.Ghana",
      "url": "https://play.google.com/store/apps/details?id=com.asemob.radioapp.Ghana",
      "icon": "https://play-lh.googleusercontent.com/fs0UNSz_f9vEYVMFAMahaNtMtPBYdfs8oZMGToheCqb05dJh8EoSaYirPjla06ACNA",
      "developer": "Ase.Mob",
      "developerId": "8797606602150852799",
      "priceText": "FREE",
      "price": 0,
      "free": true,
      "summary": "Choose your favorite radio station from the GHANA and listen live 📻 .",
      "scoreText": "0.0",
      "score": 0
    },
    {
      "title": "Telugu Radio Stations: Radio Telugu, రేడియో తెలుగు",
      "appId": "com.asemob.radioapp.telugu",
      "url": "https://play.google.com/store/apps/details?id=com.asemob.radioapp.telugu",
      "icon": "https://play-lh.googleusercontent.com/PXThGIqpdp4aN40mXsbCw1OgsQKcBao83CnWqwcVj8-FTSRqeZm84nkPDSyUBBfjuEdy",
      "developer": "Ase.Mob",
      "developerId": "8797606602150852799",
      "priceText": "FREE",
      "price": 0,
      "free": true,
      "summary": "Choose your favorite radio station from the TELUGU and listen live 📻 .",
      "scoreText": "4.4",
      "score": 4.367089
    },
    {
      "title": "USA Radio Stations: Radio United States",
      "appId": "com.asemob.radioapp.UnitedStates",
      "url": "https://play.google.com/store/apps/details?id=com.asemob.radioapp.UnitedStates",
      "icon": "https://play-lh.googleusercontent.com/iOEy7XUoIyfIL23Sg5Cq-6qwE80FCXAI2DcHRvHtae9XuVEAxec6CbQ8xxqk041isPQ",
      "developer": "Ase.Mob",
      "developerId": "8797606602150852799",
      "priceText": "FREE",
      "price": 0,
      "free": true,
      "summary": "Choose your favorite radio station from the UNITED STATES and listen live 📻 .",
      "scoreText": "0.0",
      "score": 0
    },
    {
      "title": "Azerbaijan Radio Stations: Radio Azerbaijan",
      "appId": "com.asemob.radioapp.Azerbaijan",
      "url": "https://play.google.com/store/apps/details?id=com.asemob.radioapp.Azerbaijan",
      "icon": "https://play-lh.googleusercontent.com/pkpIk2htl2wJqYjsNNV6imOaEdvmz1FEhdkOaJx022KtPbVy-_i2-BbMvCYVlUAu4Z0",
      "developer": "Ase.Mob",
      "developerId": "8797606602150852799",
      "priceText": "FREE",
      "price": 0,
      "free": true,
      "summary": "Choose your favorite radio station from the AZERBAIJAN and listen live 📻 .",
      "scoreText": "0.0",
      "score": 0
    }
  ]
}
